j_chess_client_manager/__init__.py
j_chess_client_manager/__main__.py
j_chess_client_manager/bot_manager.py
j_chess_client_manager/chess/__init__.py
j_chess_client_manager/chess/pieces.py
j_chess_client_manager/clients/__init__.py
j_chess_client_manager/clients/ai_wrapper.py
j_chess_client_manager/clients/board.py
j_chess_client_manager/clients/metrics.py
j_chess_client_manager/clients/refresh.py
j_chess_client_manager/clients/tournament.py
j_chess_client_manager/logging/__init__.py
j_chess_client_manager/ui/__init__.py
j_chess_client_manager/ui/frames/__init__.py
j_chess_client_manager/ui/frames/client_view.py
j_chess_client_manager/ui/frames/main_frame.py
j_chess_client_manager/ui/utilities/__init__.py
j_chess_client_manager/ui/widgets/__init__.py
j_chess_client_manager/ui/widgets/chessboard.py
j_chess_client_manager/ui/widgets/log.py
j_chess_client_manager-0.3.2.dist-info/AUTHORS.rst
j_chess_client_manager-0.3.2.dist-info/LICENSE
j_chess_client_manager-0.3.2.dist-info/METADATA
j_chess_client_manager-0.3.2.dist-info/WHEEL
j_chess_client_manager-0.3.2.dist-info/entry_points.txt
j_chess_client_manager-0.3.2.dist-info/top_level.txt
j_chess_client_manager-0.3.2.dist-info/RECORD
