Metadata-Version: 2.1
Name: j-chess-client-manager
Version: 0.3.2
Summary: Manager for clients designed for the awesome j-chess-server using the j-chess-lib for python
Home-page: https://github.com/RedRem95/j_chess_client_manager
Author: RedRem95
Author-email: redrem@botschmot.de
License: GNU General Public License v3
Keywords: j_chess_client_manager
Platform: UNKNOWN
Classifier: Development Status :: 2 - Pre-Alpha
Classifier: Intended Audience :: Developers
Classifier: License :: OSI Approved :: GNU General Public License v3 (GPLv3)
Classifier: Natural Language :: English
Classifier: Programming Language :: Python :: 3
Classifier: Programming Language :: Python :: 3.6
Classifier: Programming Language :: Python :: 3.7
Classifier: Programming Language :: Python :: 3.8
Classifier: Programming Language :: Python :: 3.9
Requires-Python: >=3.6
License-File: LICENSE
License-File: AUTHORS.rst
Requires-Dist: j-chess-lib (>=0.7.0)
Requires-Dist: asciimatics
Requires-Dist: pyperclip
